README.md
setup.py
calorie_utils/__init__.py
calorie_utils/calorie_api.py
calorie_utils.egg-info/PKG-INFO
calorie_utils.egg-info/SOURCES.txt
calorie_utils.egg-info/dependency_links.txt
calorie_utils.egg-info/requires.txt
calorie_utils.egg-info/top_level.txt
calorie_utils/test/__init__.py
calorie_utils/test/test_calorie_api.py