Metadata-Version: 2.2
Name: calorie_utils
Version: 0.1.2
Summary: A Python library for fetching calorie and macronutrient data from USDA FoodData Central.
Home-page: https://github.com/yourusername/calorie_utils
Author: Your Name
Author-email: your_email@example.com
Classifier: Programming Language :: Python :: 3
Classifier: License :: OSI Approved :: MIT License
Classifier: Operating System :: OS Independent
Requires-Python: >=3.6
Requires-Dist: requests
Dynamic: author
Dynamic: author-email
Dynamic: classifier
Dynamic: description
Dynamic: description-content-type
Dynamic: home-page
Dynamic: requires-dist
Dynamic: requires-python
Dynamic: summary
